openkit/__init__.py
openkit/api/__init__.py
openkit/api/action.py
openkit/api/composite.py
openkit/api/constants.py
openkit/api/openkit.py
openkit/api/openkit_object.py
openkit/api/root_action.py
openkit/api/session.py
openkit/api/web_request_tracer.py
openkit/core/__init__.py
openkit/core/beacon_sender.py
openkit/core/session_watchdog.py
openkit/core/caching/__init__.py
openkit/core/caching/beacon_cache.py
openkit/core/caching/beacon_key.py
openkit/core/caching/evictor.py
openkit/core/communication/__init__.py
openkit/core/communication/beacon_abstract.py
openkit/core/communication/beacon_capture_off.py
openkit/core/communication/beacon_capture_on.py
openkit/core/communication/beacon_flush.py
openkit/core/communication/beacon_init.py
openkit/core/communication/beacon_terminal.py
openkit/core/communication/countdown_latch.py
openkit/core/communication/state_utils.py
openkit/core/configuration/__init__.py
openkit/core/configuration/beacon_configuration.py
openkit/core/configuration/http_client_configuration.py
openkit/core/configuration/openkit_configuration.py
openkit/core/configuration/privacy_configuration.py
openkit/core/configuration/server_configuration.py
openkit/core/objects/__init__.py
openkit/core/objects/base_action.py
openkit/core/objects/leaf_action.py
openkit/core/objects/null_action.py
openkit/core/objects/null_root_action.py
openkit/core/objects/null_session.py
openkit/core/objects/null_web_request_tracer.py
openkit/core/objects/root_action.py
openkit/core/objects/session.py
openkit/core/objects/session_creator.py
openkit/core/objects/session_proxy.py
openkit/core/objects/web_request_tracer.py
openkit/protocol/__init__.py
openkit/protocol/beacon.py
openkit/protocol/event_type.py
openkit/protocol/http_client.py
openkit/protocol/response_attributes.py
openkit/protocol/status_response.py
openkit/providers/__init__.py
openkit/providers/session_id.py
openkit/vendor/__init__.py
openkit/vendor/mureq/LICENSE
openkit/vendor/mureq/__init__.py
openkit-1.0.31.dist-info/licenses/LICENSE
openkit-1.0.31.dist-info/WHEEL
openkit-1.0.31.dist-info/METADATA
openkit-1.0.31.dist-info/RECORD
