Metadata-Version: 2.4
Name: openkit
Version: 1.0.31
Summary: Python implementation of Dynatrace OpenKit.
Author-email: David Lopes <david.ribeiro.lopes@gmail.com>
Classifier: License :: OSI Approved :: MIT License
License-File: LICENSE
Project-URL: Home, https://github.com/dlopes7/dynatrace-openkit-python
